probot_tax/__init__.py
probot_tax-0.1.3.dist-info/METADATA
probot_tax-0.1.3.dist-info/WHEEL
probot_tax-0.1.3.dist-info/top_level.txt
probot_tax-0.1.3.dist-info/RECORD
