Metadata-Version: 2.1
Name: probot_tax
Version: 0.1.3
Summary: A simple library to calculate ProBot tax (5%) with full input handling and output formatting
Home-page: https://github.com/AdhamT1/probot-tax/
Author: Adham Hamdy
Author-email: example@example.com
Classifier: Programming Language :: Python :: 3
Classifier: License :: OSI Approved :: MIT License
Requires-Python: >=3.6
